MANIFEST.in
Readme.txt
setup.py
automodinit/__init__.py
automodinit/automodinit.py
automodinit/foo.py
automodinit.egg-info/PKG-INFO
automodinit.egg-info/SOURCES.txt
automodinit.egg-info/dependency_links.txt
automodinit.egg-info/top_level.txt