Metadata-Version: 1.1
Name: automodinit
Version: 0.16
Summary: Solves the problem of forgetting to keep __init__.py files up to date
Home-page: http://pypi.python.org/pypi/automodinit
Author: Niall Douglas
Author-email: UNKNOWN
License: MIT
Platform: UNKNOWN
Classifier: Development Status :: 6 - Mature
Classifier: Intended Audience :: Developers
Classifier: Topic :: Software Development :: Build Tools
Classifier: License :: OSI Approved :: MIT License
Classifier: Programming Language :: Python :: 2
Classifier: Programming Language :: Python :: 3
